{
  "type": "minecraft:block",
  "pools": [
    {
      "bonus_rolls": 0.0,
      "entries": [
        {
          "type": "minecraft:alternatives",
          "children": [
            {
              "type": "minecraft:item",
              "conditions": [
                {
                  "condition": "minecraft:match_tool",
                  "predicate": {
                    "predicates": {
                      "minecraft:enchantments": [
                        {
                          "enchantments": "minecraft:silk_touch",
                          "levels": {
                            "min": 1
                          }
                        }
                      ]
                    }
                  }
                }
              ],
              "functions": [
                {
                  "function": "minecraft:copy_components",
                  "source": "block_entity"
                },
                {
                  "block": "colourfulclocks:bornholm_middle_stripped_bamboo",
                  "function": "minecraft:copy_state",
                  "properties": [
                    "door_type"
                  ]
                }
              ],
              "name": "colourfulclocks:bornholm_middle_stripped_bamboo"
            },
            {
              "type": "minecraft:item",
              "name": "colourfulclocks:bornholm_middle_stripped_bamboo"
            }
          ]
        }
      ],
      "rolls": 1.0
    }
  ]
}